device/__init__.py
device/device.cp38-win_amd64.pyd
windows_capture_device_list-1.1.0.data/data/LICENSE
windows_capture_device_list-1.1.0.data/data/README.md
windows_capture_device_list-1.1.0.dist-info/LICENSE
windows_capture_device_list-1.1.0.dist-info/METADATA
windows_capture_device_list-1.1.0.dist-info/WHEEL
windows_capture_device_list-1.1.0.dist-info/top_level.txt
windows_capture_device_list-1.1.0.dist-info/RECORD
